kruxpy/__init__.py
kruxpy/client.py
kruxpy/tests/__init__.py
kruxpy/tests/test_linting.py
kruxpy-0.0.1.dist-info/LICENSE
kruxpy-0.0.1.dist-info/METADATA
kruxpy-0.0.1.dist-info/WHEEL
kruxpy-0.0.1.dist-info/top_level.txt
kruxpy-0.0.1.dist-info/RECORD
